dagster_teradata/__init__.py
dagster_teradata/constants.py
dagster_teradata/resources.py
dagster_teradata/teradata_compute_cluster_manager.py
dagster_teradata/ttu/__init__.py
dagster_teradata/ttu/bteq.py
dagster_teradata/ttu/tpt.py
dagster_teradata/ttu/tpt_executer.py
dagster_teradata/ttu/utils/bteq_util.py
dagster_teradata/ttu/utils/encryption_utils.py
dagster_teradata/ttu/utils/tpt_util.py
dagster_teradata-0.0.7.dist-info/METADATA
dagster_teradata-0.0.7.dist-info/WHEEL
dagster_teradata-0.0.7.dist-info/top_level.txt
dagster_teradata-0.0.7.dist-info/RECORD
