Metadata-Version: 2.4
Name: dagster-teradata
Version: 0.0.7
Summary: <insert description here>
Requires-Python: >=3.8
Requires-Dist: dagster>=1.8.0
Requires-Dist: teradatasql
Requires-Dist: paramiko
Provides-Extra: azure
Requires-Dist: dagster-azure; extra == "azure"
Provides-Extra: aws
Requires-Dist: boto3; extra == "aws"
Requires-Dist: dagster-aws; extra == "aws"
